{"$schema": "http://cyclonedx.org/schema/bom-1.4.schema.json", "bomFormat": "CycloneDX", "specVersion": "1.4", "serialNumber": "urn:uuid:c6671d70-118b-4aa9-b485-c7bacbc7c1c9", "version": 1, "metadata": {"timestamp": "2022-05-20T20:08:14.798101+00:00", "tools": [{"vendor": "CycloneDX", "name": "cyclonedx-bom", "version": "3.2.1"}, {"vendor": "CycloneDX", "name": "cyclonedx-python-lib", "version": "2.4.0", "externalReferences": [{"url": "https://cyclonedx.github.io/cyclonedx-python-lib/", "type": "documentation"}, {"url": "https://github.com/CycloneDX/cyclonedx-python-lib/blob/main/CHANGELOG.md", "type": "release-notes"}, {"url": "https://github.com/CycloneDX/cyclonedx-python-lib", "type": "vcs"}, {"url": "https://github.com/CycloneDX/cyclonedx-python-lib/blob/main/LICENSE", "type": "license"}, {"url": "https://pypi.org/project/cyclonedx-python-lib/", "type": "distribution"}, {"url": "https://github.com/CycloneDX/cyclonedx-python-lib/actions", "type": "build-system"}, {"url": "https://cyclonedx.org", "type": "website"}, {"url": "https://github.com/CycloneDX/cyclonedx-python-lib/issues", "type": "issue-tracker"}]}]}, "components": [{"type": "library", "bom-ref": "e9cdef61-17e3-4e87-9b91-03af1682e284", "name": "beautifulsoup4", "version": "4.11.1", "purl": "pkg:pypi/beautifulsoup4@4.11.1"}, {"type": "library", "bom-ref": "499b1a5d-59da-44e9-b99a-ea85ee09c7c7", "name": "iniconfig", "version": "1.1.1", "purl": "pkg:pypi/iniconfig@1.1.1"}, {"type": "library", "bom-ref": "a8ac8f34-497f-471a-acd1-97361b5b45a5", "name": "flake8", "version": "4.0.1", "purl": "pkg:pypi/flake8@4.0.1"}, {"type": "library", "bom-ref": "df158aa7-16af-413b-9d7d-3df81dc98fb6", "name": "PyYAML", "version": "6.0", "purl": "pkg:pypi/pyyaml@6.0"}, {"type": "library", "bom-ref": "fb93be00-ce8c-4b37-8895-63c6d0e81f13", "name": "idna", "version": "3.3", "purl": "pkg:pypi/idna@3.3"}, {"type": "library", "bom-ref": "a6ada84f-3253-46b6-8fc4-b5e87dbef570", "name": "Jinja2", "version": "3.1.2", "purl": "pkg:pypi/jinja2@3.1.2"}, {"type": "library", "bom-ref": "eafe16f2-969b-4a93-86d2-2e99e7e1c9d8", "name": "types-toml", "version": "0.10.7", "purl": "pkg:pypi/types-toml@0.10.7"}, {"type": "library", "bom-ref": "ec1a7a48-e7dd-46ac-94ec-98e16d89b21a", "name": "packageurl-python", "version": "0.9.9", "purl": "pkg:pypi/packageurl-python@0.9.9"}, {"type": "library", "bom-ref": "004ec616-7d04-4ccb-9b16-f00b4c8dee85", "name": "Pygments", "version": "2.12.0", "purl": "pkg:pypi/pygments@2.12.0"}, {"type": "library", "bom-ref": "c740398c-0c7f-4911-9cd2-ac958cdd48cd", "name": "pyinstaller", "version": "5.1", "purl": "pkg:pypi/pyinstaller@5.1"}, {"type": "library", "bom-ref": "640b9cfd-2db7-46c5-a95a-e1a8e90ac653", "name": "pyinstaller-hooks-contrib", "version": "2022.5", "purl": "pkg:pypi/pyinstaller-hooks-contrib@2022.5"}, {"type": "library", "bom-ref": "e0f82253-8f7f-4141-8e10-6d4baabc1178", "name": "gitdb", "version": "4.0.9", "purl": "pkg:pypi/gitdb@4.0.9"}, {"type": "library", "bom-ref": "4bf70c4b-a9a7-4ee9-8a22-93497b57e1c9", "name": "altgraph", "version": "0.17.2", "purl": "pkg:pypi/altgraph@0.17.2"}, {"type": "library", "bom-ref": "fb8b6714-1d47-4117-add3-a8d41afdd17f", "name": "MarkupSafe", "version": "2.1.1", "purl": "pkg:pypi/markupsafe@2.1.1"}, {"type": "library", "bom-ref": "75068a25-b4eb-409b-a6e5-1aff8c94ee43", "name": "requests", "version": "2.27.1", "purl": "pkg:pypi/requests@2.27.1"}, {"type": "library", "bom-ref": "325a803f-3be3-4344-83dc-68ce2e2702dc", "name": "urllib3", "version": "1.26.9", "purl": "pkg:pypi/urllib3@1.26.9"}, {"type": "library", "bom-ref": "699e3e85-d4c1-44cb-bf78-38441981fa0f", "name": "stevedore", "version": "3.5.0", "purl": "pkg:pypi/stevedore@3.5.0"}, {"type": "library", "bom-ref": "dcc2203b-8a33-47a8-b937-511144cdb434", "name": "pyparsing", "version": "3.0.9", "purl": "pkg:pypi/pyparsing@3.0.9"}, {"type": "library", "bom-ref": "26deb96c-c69d-41b9-9c20-b359cf7c9b7e", "name": "pip-requirements-parser", "version": "31.2.0", "purl": "pkg:pypi/pip-requirements-parser@31.2.0"}, {"type": "library", "bom-ref": "4f882b9f-84ff-4c57-87a9-7cab141eab46", "name": "astroid", "version": "2.11.5", "purl": "pkg:pypi/astroid@2.11.5"}, {"type": "library", "bom-ref": "b9a5384b-e8dd-4303-acd7-78896f0e5ce4", "name": "soupsieve", "version": "2.3.2.post1", "purl": "pkg:pypi/soupsieve@2.3.2.post1"}, {"type": "library", "bom-ref": "fbb2ada2-effb-4db9-8949-9936195af623", "name": "py", "version": "1.11.0", "purl": "pkg:pypi/py@1.11.0"}, {"type": "library", "bom-ref": "de3eec84-06c8-403c-b821-bfb59b1e667c", "name": "pycodestyle", "version": "2.8.0", "purl": "pkg:pypi/pycodestyle@2.8.0"}, {"type": "library", "bom-ref": "b6a83e70-3d5e-43b4-8d17-77c1efe2270c", "name": "dill", "version": "0.3.5.1", "purl": "pkg:pypi/dill@0.3.5.1"}, {"type": "library", "bom-ref": "b9f5799d-01a4-43c6-b9bd-405047893486", "name": "pytest", "version": "7.1.2", "purl": "pkg:pypi/pytest@7.1.2"}, {"type": "library", "bom-ref": "83c1d734-3315-4c94-be3a-f87eed7cfa2b", "name": "cyclonedx-bom", "version": "3.2.1", "purl": "pkg:pypi/cyclonedx-bom@3.2.1"}, {"type": "library", "bom-ref": "1fc3f869-4cfe-4801-967e-8ebb5e97779f", "name": "GitPython", "version": "3.1.27", "purl": "pkg:pypi/gitpython@3.1.27"}, {"type": "library", "bom-ref": "75a64e86-233d-440c-b96e-818e672c7a4f", "name": "tomli", "version": "2.0.1", "purl": "pkg:pypi/tomli@2.0.1"}, {"type": "library", "bom-ref": "5d0e509e-681d-4ab4-872d-e8ae76ec683c", "name": "isort", "version": "5.10.1", "purl": "pkg:pypi/isort@5.10.1"}, {"type": "library", "bom-ref": "6b63622c-9236-4c96-8d2a-661f368a96b6", "name": "mccabe", "version": "0.6.1", "purl": "pkg:pypi/mccabe@0.6.1"}, {"type": "library", "bom-ref": "ac8621a7-b0e6-4ea8-9529-1b0166eb3230", "name": "pluggy", "version": "1.0.0", "purl": "pkg:pypi/pluggy@1.0.0"}, {"type": "library", "bom-ref": "30d442e7-0ebe-49aa-b8a7-0229871ec6a5", "name": "toml", "version": "0.10.2", "purl": "pkg:pypi/toml@0.10.2"}, {"type": "library", "bom-ref": "ee331aec-7aeb-4449-9d0b-af1dff1599b1", "name": "certifi", "version": "2022.5.18.1", "purl": "pkg:pypi/certifi@2022.5.18.1"}, {"type": "library", "bom-ref": "0a149c16-07f3-4ccd-adda-4c70d476c72c", "name": "attrs", "version": "21.4.0", "purl": "pkg:pypi/attrs@21.4.0"}, {"type": "library", "bom-ref": "60c4b842-a130-4200-a1b3-bafca06f58ae", "name": "pdoc", "version": "12.0.0", "purl": "pkg:pypi/pdoc@12.0.0"}, {"type": "library", "bom-ref": "5f404b2e-cbbc-488a-bf7c-7fb4ca03ae83", "name": "coverage", "version": "6.3.3", "purl": "pkg:pypi/coverage@6.3.3"}, {"type": "library", "bom-ref": "723a1d7b-0860-4091-b5fe-7665771177c7", "name": "smmap", "version": "5.0.0", "purl": "pkg:pypi/smmap@5.0.0"}, {"type": "library", "bom-ref": "2ea5457b-86f6-4a95-aa2a-2904ee47f0ee", "name": "cyclonedx-python-lib", "version": "2.4.0", "purl": "pkg:pypi/cyclonedx-python-lib@2.4.0"}, {"type": "library", "bom-ref": "ebff46c3-ab20-4b13-8563-32a628cb4e6c", "name": "packaging", "version": "21.3", "purl": "pkg:pypi/packaging@21.3"}, {"type": "library", "bom-ref": "bb81c416-e182-4fe1-9660-20b1fa968dfb", "name": "charset-normalizer", "version": "2.0.12", "purl": "pkg:pypi/charset-normalizer@2.0.12"}, {"type": "library", "bom-ref": "7d1c386f-0bc2-47fb-a41f-fe7a4c22f3ba", "name": "PySimpleGUI", "version": "4.60.0", "purl": "pkg:pypi/pysimplegui@4.60.0"}, {"type": "library", "bom-ref": "6fdfe1c0-2bad-481e-987e-64ffad98f401", "name": "platformdirs", "version": "2.5.2", "purl": "pkg:pypi/platformdirs@2.5.2"}, {"type": "library", "bom-ref": "69ac834e-6690-47d4-9e8f-ffbc16e04d51", "name": "bandit", "version": "1.7.4", "purl": "pkg:pypi/bandit@1.7.4"}, {"type": "library", "bom-ref": "d90d96cb-a22f-490f-8aab-df30b87c0c44", "name": "types-setuptools", "version": "57.4.14", "purl": "pkg:pypi/types-setuptools@57.4.14"}, {"type": "library", "bom-ref": "e33febd1-3235-43db-bc02-1838815e839d", "name": "lazy-object-proxy", "version": "1.7.1", "purl": "pkg:pypi/lazy-object-proxy@1.7.1"}, {"type": "library", "bom-ref": "444f9fce-8da5-4e03-9d20-1d01c1ddde63", "name": "wrapt", "version": "1.14.1", "purl": "pkg:pypi/wrapt@1.14.1"}, {"type": "library", "bom-ref": "510183ec-419e-4c34-985c-6019844b00d1", "name": "pylint", "version": "2.13.9", "purl": "pkg:pypi/pylint@2.13.9"}, {"type": "library", "bom-ref": "b7fc4ba1-3339-47f8-8980-8893fb5c5091", "name": "pbr", "version": "5.9.0", "purl": "pkg:pypi/pbr@5.9.0"}, {"type": "library", "bom-ref": "dbe55cfd-9a22-4417-9c1b-8c42b3dbe4c5", "name": "pyflakes", "version": "2.4.0", "purl": "pkg:pypi/pyflakes@2.4.0"}], "dependencies": [{"ref": "e9cdef61-17e3-4e87-9b91-03af1682e284", "dependsOn": []}, {"ref": "499b1a5d-59da-44e9-b99a-ea85ee09c7c7", "dependsOn": []}, {"ref": "a8ac8f34-497f-471a-acd1-97361b5b45a5", "dependsOn": []}, {"ref": "df158aa7-16af-413b-9d7d-3df81dc98fb6", "dependsOn": []}, {"ref": "fb93be00-ce8c-4b37-8895-63c6d0e81f13", "dependsOn": []}, {"ref": "a6ada84f-3253-46b6-8fc4-b5e87dbef570", "dependsOn": []}, {"ref": "eafe16f2-969b-4a93-86d2-2e99e7e1c9d8", "dependsOn": []}, {"ref": "ec1a7a48-e7dd-46ac-94ec-98e16d89b21a", "dependsOn": []}, {"ref": "004ec616-7d04-4ccb-9b16-f00b4c8dee85", "dependsOn": []}, {"ref": "c740398c-0c7f-4911-9cd2-ac958cdd48cd", "dependsOn": []}, {"ref": "640b9cfd-2db7-46c5-a95a-e1a8e90ac653", "dependsOn": []}, {"ref": "e0f82253-8f7f-4141-8e10-6d4baabc1178", "dependsOn": []}, {"ref": "4bf70c4b-a9a7-4ee9-8a22-93497b57e1c9", "dependsOn": []}, {"ref": "fb8b6714-1d47-4117-add3-a8d41afdd17f", "dependsOn": []}, {"ref": "75068a25-b4eb-409b-a6e5-1aff8c94ee43", "dependsOn": []}, {"ref": "325a803f-3be3-4344-83dc-68ce2e2702dc", "dependsOn": []}, {"ref": "699e3e85-d4c1-44cb-bf78-38441981fa0f", "dependsOn": []}, {"ref": "dcc2203b-8a33-47a8-b937-511144cdb434", "dependsOn": []}, {"ref": "26deb96c-c69d-41b9-9c20-b359cf7c9b7e", "dependsOn": []}, {"ref": "4f882b9f-84ff-4c57-87a9-7cab141eab46", "dependsOn": []}, {"ref": "b9a5384b-e8dd-4303-acd7-78896f0e5ce4", "dependsOn": []}, {"ref": "fbb2ada2-effb-4db9-8949-9936195af623", "dependsOn": []}, {"ref": "de3eec84-06c8-403c-b821-bfb59b1e667c", "dependsOn": []}, {"ref": "b6a83e70-3d5e-43b4-8d17-77c1efe2270c", "dependsOn": []}, {"ref": "b9f5799d-01a4-43c6-b9bd-405047893486", "dependsOn": []}, {"ref": "83c1d734-3315-4c94-be3a-f87eed7cfa2b", "dependsOn": []}, {"ref": "1fc3f869-4cfe-4801-967e-8ebb5e97779f", "dependsOn": []}, {"ref": "75a64e86-233d-440c-b96e-818e672c7a4f", "dependsOn": []}, {"ref": "5d0e509e-681d-4ab4-872d-e8ae76ec683c", "dependsOn": []}, {"ref": "6b63622c-9236-4c96-8d2a-661f368a96b6", "dependsOn": []}, {"ref": "ac8621a7-b0e6-4ea8-9529-1b0166eb3230", "dependsOn": []}, {"ref": "30d442e7-0ebe-49aa-b8a7-0229871ec6a5", "dependsOn": []}, {"ref": "ee331aec-7aeb-4449-9d0b-af1dff1599b1", "dependsOn": []}, {"ref": "0a149c16-07f3-4ccd-adda-4c70d476c72c", "dependsOn": []}, {"ref": "60c4b842-a130-4200-a1b3-bafca06f58ae", "dependsOn": []}, {"ref": "5f404b2e-cbbc-488a-bf7c-7fb4ca03ae83", "dependsOn": []}, {"ref": "723a1d7b-0860-4091-b5fe-7665771177c7", "dependsOn": []}, {"ref": "2ea5457b-86f6-4a95-aa2a-2904ee47f0ee", "dependsOn": []}, {"ref": "ebff46c3-ab20-4b13-8563-32a628cb4e6c", "dependsOn": []}, {"ref": "bb81c416-e182-4fe1-9660-20b1fa968dfb", "dependsOn": []}, {"ref": "7d1c386f-0bc2-47fb-a41f-fe7a4c22f3ba", "dependsOn": []}, {"ref": "6fdfe1c0-2bad-481e-987e-64ffad98f401", "dependsOn": []}, {"ref": "69ac834e-6690-47d4-9e8f-ffbc16e04d51", "dependsOn": []}, {"ref": "d90d96cb-a22f-490f-8aab-df30b87c0c44", "dependsOn": []}, {"ref": "e33febd1-3235-43db-bc02-1838815e839d", "dependsOn": []}, {"ref": "444f9fce-8da5-4e03-9d20-1d01c1ddde63", "dependsOn": []}, {"ref": "510183ec-419e-4c34-985c-6019844b00d1", "dependsOn": []}, {"ref": "b7fc4ba1-3339-47f8-8980-8893fb5c5091", "dependsOn": []}, {"ref": "dbe55cfd-9a22-4417-9c1b-8c42b3dbe4c5", "dependsOn": []}]}