{"$schema": "http://cyclonedx.org/schema/bom-1.4.schema.json", "bomFormat": "CycloneDX", "specVersion": "1.4", "serialNumber": "urn:uuid:53c670e3-49df-4bff-b959-2287665f3133", "version": 1, "metadata": {"timestamp": "2022-05-17T13:43:49.515996+00:00", "tools": [{"vendor": "CycloneDX", "name": "cyclonedx-bom", "version": "3.2.1"}, {"vendor": "CycloneDX", "name": "cyclonedx-python-lib", "version": "2.3.0", "externalReferences": [{"url": "https://cyclonedx.org", "type": "website"}, {"url": "https://cyclonedx.github.io/cyclonedx-python-lib/", "type": "documentation"}, {"url": "https://github.com/CycloneDX/cyclonedx-python-lib/actions", "type": "build-system"}, {"url": "https://github.com/CycloneDX/cyclonedx-python-lib/issues", "type": "issue-tracker"}, {"url": "https://github.com/CycloneDX/cyclonedx-python-lib/blob/main/CHANGELOG.md", "type": "release-notes"}, {"url": "https://pypi.org/project/cyclonedx-python-lib/", "type": "distribution"}, {"url": "https://github.com/CycloneDX/cyclonedx-python-lib/blob/main/LICENSE", "type": "license"}, {"url": "https://github.com/CycloneDX/cyclonedx-python-lib", "type": "vcs"}]}]}, "components": [{"type": "library", "bom-ref": "a4b49259-54aa-4e17-9141-0ee6cf5ea5dc", "name": "urllib3", "version": "1.26.9", "purl": "pkg:pypi/urllib3@1.26.9"}, {"type": "library", "bom-ref": "0e6d487e-d4ca-431c-bbc9-d5891f26787a", "name": "pbr", "version": "5.9.0", "purl": "pkg:pypi/pbr@5.9.0"}, {"type": "library", "bom-ref": "da0c0f6b-9d95-4578-9e36-7b80c590bf4c", "name": "packaging", "version": "21.3", "purl": "pkg:pypi/packaging@21.3"}, {"type": "library", "bom-ref": "e5e3ad49-bd8b-4f66-aa35-9b15dd2189b2", "name": "MarkupSafe", "version": "2.1.1", "purl": "pkg:pypi/markupsafe@2.1.1"}, {"type": "library", "bom-ref": "036c244f-3ef6-457c-9286-4638b2181254", "name": "packageurl-python", "version": "0.9.9", "purl": "pkg:pypi/packageurl-python@0.9.9"}, {"type": "library", "bom-ref": "199a2859-52eb-4d69-b159-a503eae63bc5", "name": "wrapt", "version": "1.14.1", "purl": "pkg:pypi/wrapt@1.14.1"}, {"type": "library", "bom-ref": "1bb323a5-77a5-4058-8d3e-ae807441ffbc", "name": "astroid", "version": "2.11.5", "purl": "pkg:pypi/astroid@2.11.5"}, {"type": "library", "bom-ref": "3e5e3ba2-8b5f-477c-a0a3-df7c44e4ebb1", "name": "Pygments", "version": "2.12.0", "purl": "pkg:pypi/pygments@2.12.0"}, {"type": "library", "bom-ref": "b435e31e-b249-4ea6-957d-c4000b52c628", "name": "pyparsing", "version": "3.0.9", "purl": "pkg:pypi/pyparsing@3.0.9"}, {"type": "library", "bom-ref": "6c66010e-6aae-44c2-a571-6de75825332d", "name": "attrs", "version": "21.4.0", "purl": "pkg:pypi/attrs@21.4.0"}, {"type": "library", "bom-ref": "75b8d16a-a6b2-46c7-91d4-e7accfd48bb6", "name": "charset-normalizer", "version": "2.0.12", "purl": "pkg:pypi/charset-normalizer@2.0.12"}, {"type": "library", "bom-ref": "5b50b2b8-4fba-4d94-a55a-eb70a94e3130", "name": "requests", "version": "2.27.1", "purl": "pkg:pypi/requests@2.27.1"}, {"type": "library", "bom-ref": "b325dbc5-184c-4d22-812d-5b65cb576336", "name": "py", "version": "1.11.0", "purl": "pkg:pypi/py@1.11.0"}, {"type": "library", "bom-ref": "c2ed499b-cf77-41e6-9875-2ca625405450", "name": "iniconfig", "version": "1.1.1", "purl": "pkg:pypi/iniconfig@1.1.1"}, {"type": "library", "bom-ref": "f9a30a67-641d-4002-88bb-9e334fbbc446", "name": "coverage", "version": "6.3.3", "purl": "pkg:pypi/coverage@6.3.3"}, {"type": "library", "bom-ref": "ffec2bba-f3c7-42a3-9eeb-20bee7b31b63", "name": "pyflakes", "version": "2.4.0", "purl": "pkg:pypi/pyflakes@2.4.0"}, {"type": "library", "bom-ref": "6a1b65b4-5071-4778-b189-cbc1d01b4189", "name": "smmap", "version": "5.0.0", "purl": "pkg:pypi/smmap@5.0.0"}, {"type": "library", "bom-ref": "fa9561d5-edb3-4b2d-b5fc-9131d17ca16b", "name": "isort", "version": "5.10.1", "purl": "pkg:pypi/isort@5.10.1"}, {"type": "library", "bom-ref": "b6da3542-b060-459b-9161-be681b79af3b", "name": "flake8", "version": "4.0.1", "purl": "pkg:pypi/flake8@4.0.1"}, {"type": "library", "bom-ref": "f58dfc0f-7fb1-4420-9b4e-970a3af4bb36", "name": "altgraph", "version": "0.17.2", "purl": "pkg:pypi/altgraph@0.17.2"}, {"type": "library", "bom-ref": "c3eec805-e0be-4c2d-87a4-b58d62b14f51", "name": "platformdirs", "version": "2.5.2", "purl": "pkg:pypi/platformdirs@2.5.2"}, {"type": "library", "bom-ref": "978e7d64-f51e-4cc7-8dfb-ba061ccdfebe", "name": "dill", "version": "0.3.4", "purl": "pkg:pypi/dill@0.3.4"}, {"type": "library", "bom-ref": "357d3fed-fbb1-481f-90ce-805b1cd22ec7", "name": "bandit", "version": "1.7.4", "purl": "pkg:pypi/bandit@1.7.4"}, {"type": "library", "bom-ref": "845e4421-a86d-4448-9443-16a4da18b592", "name": "pip-requirements-parser", "version": "31.2.0", "purl": "pkg:pypi/pip-requirements-parser@31.2.0"}, {"type": "library", "bom-ref": "9afc1d25-0a04-44c3-a18a-8f00f62b8468", "name": "toml", "version": "0.10.2", "purl": "pkg:pypi/toml@0.10.2"}, {"type": "library", "bom-ref": "d93e811b-d577-49e9-880d-7d8e90686fc1", "name": "GitPython", "version": "3.1.27", "purl": "pkg:pypi/gitpython@3.1.27"}, {"type": "library", "bom-ref": "16b4ade7-1d1a-46d0-8ea4-ee2a71fa2e6e", "name": "stevedore", "version": "3.5.0", "purl": "pkg:pypi/stevedore@3.5.0"}, {"type": "library", "bom-ref": "19257c27-f83a-4fc2-b937-12c0ea273a92", "name": "beautifulsoup4", "version": "4.11.1", "purl": "pkg:pypi/beautifulsoup4@4.11.1"}, {"type": "library", "bom-ref": "9933551c-1b24-4683-a157-e4a59d92189f", "name": "cyclonedx-bom", "version": "3.2.1", "purl": "pkg:pypi/cyclonedx-bom@3.2.1"}, {"type": "library", "bom-ref": "fedd9408-c055-4aa7-9102-a29c55ad8b0d", "name": "gitdb", "version": "4.0.9", "purl": "pkg:pypi/gitdb@4.0.9"}, {"type": "library", "bom-ref": "637e4bc8-7d82-4f6a-83dc-39330cb333c6", "name": "mccabe", "version": "0.6.1", "purl": "pkg:pypi/mccabe@0.6.1"}, {"type": "library", "bom-ref": "5011d7be-f657-46a0-8ef0-255070daf96b", "name": "pycodestyle", "version": "2.8.0", "purl": "pkg:pypi/pycodestyle@2.8.0"}, {"type": "library", "bom-ref": "35a8d972-87d5-44e1-b8e2-4a71437d745d", "name": "pyinstaller", "version": "5.0.1", "purl": "pkg:pypi/pyinstaller@5.0.1"}, {"type": "library", "bom-ref": "80b9b450-4592-48c6-a21f-4b75013c9553", "name": "types-toml", "version": "0.10.7", "purl": "pkg:pypi/types-toml@0.10.7"}, {"type": "library", "bom-ref": "9a198a1e-5999-4bb7-834a-9c4e58df3a4c", "name": "certifi", "version": "2021.10.8", "purl": "pkg:pypi/certifi@2021.10.8"}, {"type": "library", "bom-ref": "64694f8e-43a0-4c40-b48a-abc8acc6db58", "name": "pytest", "version": "7.1.2", "purl": "pkg:pypi/pytest@7.1.2"}, {"type": "library", "bom-ref": "8ac9519f-31aa-41e6-ac4d-4cae82725d51", "name": "lazy-object-proxy", "version": "1.7.1", "purl": "pkg:pypi/lazy-object-proxy@1.7.1"}, {"type": "library", "bom-ref": "a6ff658d-bd44-4de3-a967-9f162dd71967", "name": "PyYAML", "version": "6.0", "purl": "pkg:pypi/pyyaml@6.0"}, {"type": "library", "bom-ref": "a29bfafb-1016-4e64-90e7-3efe0b6d5c23", "name": "idna", "version": "3.3", "purl": "pkg:pypi/idna@3.3"}, {"type": "library", "bom-ref": "1f630f3c-74ef-4d2d-9289-c3faf56f5b90", "name": "soupsieve", "version": "2.3.2.post1", "purl": "pkg:pypi/soupsieve@2.3.2.post1"}, {"type": "library", "bom-ref": "6c540163-8083-40a3-9782-9c2ddefe63a7", "name": "pylint", "version": "2.13.9", "purl": "pkg:pypi/pylint@2.13.9"}, {"type": "library", "bom-ref": "df184647-3e6e-4023-9234-9dd81b7eb960", "name": "Jinja2", "version": "3.1.2", "purl": "pkg:pypi/jinja2@3.1.2"}, {"type": "library", "bom-ref": "1485ff7b-627a-45aa-bfb7-97d0fc920d87", "name": "pdoc", "version": "12.0.0", "purl": "pkg:pypi/pdoc@12.0.0"}, {"type": "library", "bom-ref": "88237879-b13c-45f0-a7ba-bb0010f6e0be", "name": "types-setuptools", "version": "57.4.14", "purl": "pkg:pypi/types-setuptools@57.4.14"}, {"type": "library", "bom-ref": "a66850cd-1e72-4009-a988-56774405f46a", "name": "pluggy", "version": "1.0.0", "purl": "pkg:pypi/pluggy@1.0.0"}, {"type": "library", "bom-ref": "f3f958ab-8240-43f9-b40d-adb9249ec512", "name": "tomli", "version": "2.0.1", "purl": "pkg:pypi/tomli@2.0.1"}, {"type": "library", "bom-ref": "799d03a7-5493-4063-a908-57c9f93530ce", "name": "cyclonedx-python-lib", "version": "2.3.0", "purl": "pkg:pypi/cyclonedx-python-lib@2.3.0"}, {"type": "library", "bom-ref": "12790a9c-56cb-40d4-977d-ba032d14a47d", "name": "pyinstaller-hooks-contrib", "version": "2022.5", "purl": "pkg:pypi/pyinstaller-hooks-contrib@2022.5"}, {"type": "library", "bom-ref": "0517556f-0866-473e-9542-8a1c39ee7792", "name": "PySimpleGUI", "version": "4.60.0", "purl": "pkg:pypi/pysimplegui@4.60.0"}], "dependencies": [{"ref": "a4b49259-54aa-4e17-9141-0ee6cf5ea5dc", "dependsOn": []}, {"ref": "0e6d487e-d4ca-431c-bbc9-d5891f26787a", "dependsOn": []}, {"ref": "da0c0f6b-9d95-4578-9e36-7b80c590bf4c", "dependsOn": []}, {"ref": "e5e3ad49-bd8b-4f66-aa35-9b15dd2189b2", "dependsOn": []}, {"ref": "036c244f-3ef6-457c-9286-4638b2181254", "dependsOn": []}, {"ref": "199a2859-52eb-4d69-b159-a503eae63bc5", "dependsOn": []}, {"ref": "1bb323a5-77a5-4058-8d3e-ae807441ffbc", "dependsOn": []}, {"ref": "3e5e3ba2-8b5f-477c-a0a3-df7c44e4ebb1", "dependsOn": []}, {"ref": "b435e31e-b249-4ea6-957d-c4000b52c628", "dependsOn": []}, {"ref": "6c66010e-6aae-44c2-a571-6de75825332d", "dependsOn": []}, {"ref": "75b8d16a-a6b2-46c7-91d4-e7accfd48bb6", "dependsOn": []}, {"ref": "5b50b2b8-4fba-4d94-a55a-eb70a94e3130", "dependsOn": []}, {"ref": "b325dbc5-184c-4d22-812d-5b65cb576336", "dependsOn": []}, {"ref": "c2ed499b-cf77-41e6-9875-2ca625405450", "dependsOn": []}, {"ref": "f9a30a67-641d-4002-88bb-9e334fbbc446", "dependsOn": []}, {"ref": "ffec2bba-f3c7-42a3-9eeb-20bee7b31b63", "dependsOn": []}, {"ref": "6a1b65b4-5071-4778-b189-cbc1d01b4189", "dependsOn": []}, {"ref": "fa9561d5-edb3-4b2d-b5fc-9131d17ca16b", "dependsOn": []}, {"ref": "b6da3542-b060-459b-9161-be681b79af3b", "dependsOn": []}, {"ref": "f58dfc0f-7fb1-4420-9b4e-970a3af4bb36", "dependsOn": []}, {"ref": "c3eec805-e0be-4c2d-87a4-b58d62b14f51", "dependsOn": []}, {"ref": "978e7d64-f51e-4cc7-8dfb-ba061ccdfebe", "dependsOn": []}, {"ref": "357d3fed-fbb1-481f-90ce-805b1cd22ec7", "dependsOn": []}, {"ref": "845e4421-a86d-4448-9443-16a4da18b592", "dependsOn": []}, {"ref": "9afc1d25-0a04-44c3-a18a-8f00f62b8468", "dependsOn": []}, {"ref": "d93e811b-d577-49e9-880d-7d8e90686fc1", "dependsOn": []}, {"ref": "16b4ade7-1d1a-46d0-8ea4-ee2a71fa2e6e", "dependsOn": []}, {"ref": "19257c27-f83a-4fc2-b937-12c0ea273a92", "dependsOn": []}, {"ref": "9933551c-1b24-4683-a157-e4a59d92189f", "dependsOn": []}, {"ref": "fedd9408-c055-4aa7-9102-a29c55ad8b0d", "dependsOn": []}, {"ref": "637e4bc8-7d82-4f6a-83dc-39330cb333c6", "dependsOn": []}, {"ref": "5011d7be-f657-46a0-8ef0-255070daf96b", "dependsOn": []}, {"ref": "35a8d972-87d5-44e1-b8e2-4a71437d745d", "dependsOn": []}, {"ref": "80b9b450-4592-48c6-a21f-4b75013c9553", "dependsOn": []}, {"ref": "9a198a1e-5999-4bb7-834a-9c4e58df3a4c", "dependsOn": []}, {"ref": "64694f8e-43a0-4c40-b48a-abc8acc6db58", "dependsOn": []}, {"ref": "8ac9519f-31aa-41e6-ac4d-4cae82725d51", "dependsOn": []}, {"ref": "a6ff658d-bd44-4de3-a967-9f162dd71967", "dependsOn": []}, {"ref": "a29bfafb-1016-4e64-90e7-3efe0b6d5c23", "dependsOn": []}, {"ref": "1f630f3c-74ef-4d2d-9289-c3faf56f5b90", "dependsOn": []}, {"ref": "6c540163-8083-40a3-9782-9c2ddefe63a7", "dependsOn": []}, {"ref": "df184647-3e6e-4023-9234-9dd81b7eb960", "dependsOn": []}, {"ref": "1485ff7b-627a-45aa-bfb7-97d0fc920d87", "dependsOn": []}, {"ref": "88237879-b13c-45f0-a7ba-bb0010f6e0be", "dependsOn": []}, {"ref": "a66850cd-1e72-4009-a988-56774405f46a", "dependsOn": []}, {"ref": "f3f958ab-8240-43f9-b40d-adb9249ec512", "dependsOn": []}, {"ref": "799d03a7-5493-4063-a908-57c9f93530ce", "dependsOn": []}, {"ref": "12790a9c-56cb-40d4-977d-ba032d14a47d", "dependsOn": []}, {"ref": "0517556f-0866-473e-9542-8a1c39ee7792", "dependsOn": []}]}